codesearch/__init__.py
codesearch/cli.py
codesearch/indexer.py
codesearch-0.1.0.dist-info/METADATA
codesearch-0.1.0.dist-info/WHEEL
codesearch-0.1.0.dist-info/entry_points.txt
codesearch-0.1.0.dist-info/licenses/LICENSE
codesearch-0.1.0.dist-info/RECORD
