Metadata-Version: 2.3
Name: codesearch
Version: 0.1.0
Summary: A fast code search tool using Tantivy
Project-URL: Homepage, https://github.com/yourusername/codesearch
Project-URL: Bug Tracker, https://github.com/yourusername/codesearch/issues
Author-email: Ajitesh <ajiteshleo@gmail.com>
Classifier: License :: OSI Approved :: MIT License
Classifier: Operating System :: OS Independent
Classifier: Programming Language :: Python :: 3
Requires-Python: >=3.7
Requires-Dist: loguru
Requires-Dist: tantivy
